pyrsca/__init__.py
pyrsca/py.typed
pyrsca/pyrsca.cpython-314t-darwin.so
pyrsca/pyrsca.pyi
pyrsca-0.4.0.dist-info/METADATA
pyrsca-0.4.0.dist-info/WHEEL
pyrsca-0.4.0.dist-info/RECORD
