Metadata-Version: 2.4
Name: pyrsca
Version: 0.4.0
Classifier: Programming Language :: Rust
Classifier: Programming Language :: Python :: Implementation :: CPython
Classifier: Programming Language :: Python :: Implementation :: PyPy
Classifier: Programming Language :: Python :: 3
Classifier: Programming Language :: Python :: 3.7
Classifier: Programming Language :: Python :: 3.8
Classifier: Programming Language :: Python :: 3.9
Classifier: Programming Language :: Python :: 3.10
Classifier: Programming Language :: Python :: 3.11
Classifier: Programming Language :: Python :: 3.12
Classifier: Programming Language :: Python :: 3.13
Classifier: Programming Language :: Python :: 3.14
Requires-Dist: pytest>=6.0 ; extra == 'dev'
Requires-Dist: pytest-dotenv>=0.5.2 ; extra == 'dev'
Requires-Dist: maturin>=1.2,<2.0 ; extra == 'dev'
Requires-Dist: pytest-benchmark>=3.4.1 ; extra == 'dev'
Requires-Dist: pytest>=6.0 ; extra == 'test'
Requires-Dist: pytest-dotenv>=0.5.2 ; extra == 'test'
Provides-Extra: dev
Provides-Extra: test
Summary: Python bindings for rsca library
Keywords: rust,cryptography,signature
Author-email: yvictor <yvictor3141@gmail.com>
Requires-Python: >=3.7
Project-URL: Homepage, https://github.com/yvictor/rsca
Project-URL: Issues, https://github.com/yvictor/rsca/issues
Project-URL: Repository, https://github.com/yvictor/rsca
